cli_tls/__init__.py
cli_tls/main.py
cli_tls-1.0.2.dist-info/LICENSE.txt
cli_tls-1.0.2.dist-info/METADATA
cli_tls-1.0.2.dist-info/WHEEL
cli_tls-1.0.2.dist-info/entry_points.txt
cli_tls-1.0.2.dist-info/top_level.txt
cli_tls-1.0.2.dist-info/RECORD
